tencentcloud/__init__.py
tencentcloud/dbbrain/__init__.py
tencentcloud/dbbrain/v20191016/__init__.py
tencentcloud/dbbrain/v20191016/dbbrain_client.py
tencentcloud/dbbrain/v20191016/dbbrain_client_async.py
tencentcloud/dbbrain/v20191016/errorcodes.py
tencentcloud/dbbrain/v20191016/models.py
tencentcloud/dbbrain/v20210527/__init__.py
tencentcloud/dbbrain/v20210527/dbbrain_client.py
tencentcloud/dbbrain/v20210527/dbbrain_client_async.py
tencentcloud/dbbrain/v20210527/errorcodes.py
tencentcloud/dbbrain/v20210527/models.py
tencentcloud_sdk_python_dbbrain-3.1.25.dist-info/METADATA
tencentcloud_sdk_python_dbbrain-3.1.25.dist-info/WHEEL
tencentcloud_sdk_python_dbbrain-3.1.25.dist-info/top_level.txt
tencentcloud_sdk_python_dbbrain-3.1.25.dist-info/RECORD
